setup.py
src/sellpass/__init__.py
src/sellpass/announcements.py
src/sellpass/blacklist.py
src/sellpass/categories.py
src/sellpass/coupons.py
src/sellpass/customers.py
src/sellpass/customization.py
src/sellpass/dashboard.py
src/sellpass/faqs.py
src/sellpass/feedback.py
src/sellpass/groups.py
src/sellpass/listings.py
src/sellpass/orders.py
src/sellpass/products.py
src/sellpass/productsv2.py
src/sellpass/public.py
src/sellpass/shop.py
src/sellpass/tickets.py
src/sellpass_sdk.egg-info/PKG-INFO
src/sellpass_sdk.egg-info/SOURCES.txt
src/sellpass_sdk.egg-info/dependency_links.txt
src/sellpass_sdk.egg-info/top_level.txt