Metadata-Version: 2.1
Name: sellpass-sdk
Version: 1.1
Summary: Python SDK for Sellpass.
Home-page: https://github.com/sellpass/python-api-sdk
License: MIT
Keywords: sellpass sdk python sellpass-sdk
Platform: UNKNOWN
Requires-Python: >=3.6
